cac_core/__init__.py
cac_core/cli.py
cac_core/command.py
cac_core/config.py
cac_core/credentialmanager.py
cac_core/logger.py
cac_core/model.py
cac_core/output.py
cac_core/updatechecker.py
cac_core-0.5.2.dist-info/licenses/LICENSE
cac_core-0.5.2.dist-info/METADATA
cac_core-0.5.2.dist-info/WHEEL
cac_core-0.5.2.dist-info/top_level.txt
cac_core-0.5.2.dist-info/RECORD
