Metadata-Version: 2.4
Name: cac-core
Version: 0.5.2
Author-email: Ryan Punt <ryan@mirum.org>
License-Expression: MIT
Project-URL: homepage, https://mirum.org/cac-core/
Project-URL: repository, https://github.com/rpunt/cac-core
Keywords: api,framework,cli,command-lint,python,cli-tool
Classifier: Programming Language :: Python :: 3
Classifier: Operating System :: OS Independent
Requires-Python: <4.0,>=3.9
License-File: LICENSE
Requires-Dist: logger>=1.4
Requires-Dist: tabulate>=0.9.0
Requires-Dist: requests>=2.32.3
Requires-Dist: pyyaml>=6.0.2
Requires-Dist: keyring>=25.6.0
Requires-Dist: packaging>=25.0
Provides-Extra: dev
Requires-Dist: pytest>=8.3.5; extra == "dev"
Requires-Dist: pytest-cov>=6.1.1; extra == "dev"
Provides-Extra: test
Requires-Dist: pytest>=8.3.5; extra == "test"
Provides-Extra: lint
Requires-Dist: black>=23.3.0; extra == "lint"
Requires-Dist: isort>=5.12.0; extra == "lint"
Requires-Dist: pylint>=2.17.0; extra == "lint"
Provides-Extra: docs
Requires-Dist: sphinx>=7.0.0; extra == "docs"
Requires-Dist: sphinx-rtd-theme>=1.2.0; extra == "docs"
Dynamic: license-file
